{
  "$schema": "http://schema.management.azure.com/schemas/2015-01-01/deploymentTemplate.json#",
  "contentVersion": "1.0.0.0",
  "parameters": {
    "storageaccountname": {
      "defaultValue": "ststorage",
      "type": "string"
    },

    "sitename": {
      "defaultValue": "stsite",
      "type": "string"
    },

    "repoUrl": {
      "defaultValue": "",
      "type": "string"
    },

    "resourcegroup": {
      "defaultValue": "stresourcegroup",
      "type": "string"
    },

    "subscription": {
      "defaultValue": "idrequired",
      "type": "string"
    }
  },
  "variables": {},
  "resources": [
    {
      "type": "Microsoft.Web/sites",
      "kind": "functionapp",
      "name": "[parameters('sitename')]",
      "apiVersion": "2016-03-01",
      "location": "[resourceGroup().location]",
      "properties": {
        "name": "[parameters('sitename')]",
        "siteConfig": {
          "appSettings": [
            {
              "name": "AzureWebJobsDashboard",
              "value": "[concat('DefaultEndpointsProtocol=https;AccountName=',parameters('storageaccountname'),';AccountKey=',listKeys(resourceId('Microsoft.Storage/storageAccounts', parameters('storageaccountname')), '2015-05-01-preview').key1)]"
            },
            {
              "name": "AzureWebJobsStorage",
              "value": "[concat('DefaultEndpointsProtocol=https;AccountName=',parameters('storageaccountname'),';AccountKey=',listKeys(resourceId('Microsoft.Storage/storageAccounts', parameters('storageaccountname')), '2015-05-01-preview').key1)]"
            },
            {
              "name": "FUNCTIONS_EXTENSION_VERSION",
              "value": "~0.8"
            },
            {
              "name": "WEBSITE_CONTENTAZUREFILECONNECTIONSTRING",
              "value": "[concat('DefaultEndpointsProtocol=https;AccountName=',parameters('storageaccountname'),';AccountKey=',listKeys(resourceId('Microsoft.Storage/storageAccounts', parameters('storageaccountname')), '2015-05-01-preview').key1)]"
            },
            {
              "name": "WEBSITE_CONTENTSHARE",
              "value": "[toLower(parameters('sitename'))]"
            },
            {
              "name": "WEBSITE_NODE_DEFAULT_VERSION",
              "value": "4.1.2"
            }
          ]
        },
        "containerSize": 512
      },
      "dependsOn": [
        "[resourceId('Microsoft.Storage/storageAccounts', parameters('storageaccountname'))]"
      ]
    },
    {
      "type": "Microsoft.Storage/storageAccounts",
      "name": "[parameters('storageaccountname')]",
      "apiVersion": "2015-05-01-preview",
      "location": "[resourceGroup().location]",
      "properties": {
        "accountType": "Standard_LRS"
      }
    },
    {
      "apiVersion": "2015-08-01",
      "name": "web",
      "type": "sourcecontrols",
      "dependsOn": [
        "[resourceId('Microsoft.Web/sites/', parameters('storageaccountname'))]"
      ],
      "properties": {
        "RepoUrl": "https://github.com/Microsoft/BusinessPlatformApps/tree/NewsTemplate/Source/Apps/Microsoft/Released/Microsoft-NewsTemplate/Service/NewsFunction",
        "branch": "master",
        "IsManualIntegration": "true"
      }
    }
  ]
}
